{
    "id": "desc_153a",
    "name": "Regression - anchors - bottom_top",
    "tests": {
        "test_07b9": {
            "id": "test_07b9",
            "name": "Should change top, add distance to pusher bottom if locked",
            "testData": {
                "structure": {
                    "id": "page",
                    "layout": {
                        "x": 0,
                        "y": 0,
                        "width": 1265,
                        "height": 500
                    },
                    "children": [
                        {
                            "id": "comp-879d",
                            "layout": {
                                "x": 100,
                                "y": 100,
                                "width": 100,
                                "height": 60,
                                "rotationInDegrees": 0
                            }
                        },
                        {
                            "id": "comp-2f45",
                            "layout": {
                                "x": 100,
                                "y": 170,
                                "width": 100,
                                "height": 60,
                                "rotationInDegrees": 0
                            }
                        }
                    ]
                },
                "measureMap": {
                    "width": {
                        "screen": 1265,
                        "page": 1265,
                        "comp-879d": 100,
                        "comp-2f45": 100
                    },
                    "left": {
                        "page": 0,
                        "comp-879d": 100,
                        "comp-2f45": 100
                    },
                    "height": {
                        "screen": 800,
                        "page": 500,
                        "comp-879d": 90,
                        "comp-2f45": 60
                    },
                    "innerWidth": {
                        "screen": 1265,
                        "page": 1265,
                        "comp-879d": 100,
                        "comp-2f45": 100
                    },
                    "clientHeight": 800,
                    "fixed": {
                        "page": false,
                        "comp-879d": false,
                        "comp-2f45": false
                    },
                    "top": {
                        "page": 0,
                        "comp-879d": 100,
                        "comp-2f45": 170
                    },
                    "clientWidth": 1265,
                    "innerHeight": {
                        "screen": 800,
                        "page": 500,
                        "comp-879d": 90,
                        "comp-2f45": 60
                    },
                    "absoluteTop": {
                        "page": 0,
                        "comp-879d": 100,
                        "comp-2f45": 170
                    },
                    "absoluteLeft": {
                        "page": 0,
                        "comp-879d": 100,
                        "comp-2f45": 100
                    },
                    "shrinkableContainer": {},
                    "minHeight": {},
                    "collapsed": {},
                    "containerHeightMargin": {}
                },
                "expectedMeasureMap": {
                    "width": {
                        "screen": 1265,
                        "page": 1265,
                        "comp-879d": 100,
                        "comp-2f45": 100
                    },
                    "left": {
                        "page": 0,
                        "comp-879d": 100,
                        "comp-2f45": 100
                    },
                    "height": {
                        "screen": 800,
                        "page": 500,
                        "comp-879d": 90,
                        "comp-2f45": 60
                    },
                    "innerWidth": {
                        "screen": 1265,
                        "page": 1265,
                        "comp-879d": 100,
                        "comp-2f45": 100
                    },
                    "clientHeight": 800,
                    "fixed": {
                        "page": false,
                        "comp-879d": false,
                        "comp-2f45": false
                    },
                    "top": {
                        "page": 0,
                        "comp-879d": 100,
                        "comp-2f45": 200
                    },
                    "clientWidth": 1265,
                    "innerHeight": {
                        "screen": 800,
                        "page": 500,
                        "comp-879d": 90,
                        "comp-2f45": 60
                    },
                    "absoluteTop": {
                        "page": 0,
                        "comp-879d": 100,
                        "comp-2f45": 170
                    },
                    "absoluteLeft": {
                        "page": 0,
                        "comp-879d": 100,
                        "comp-2f45": 100
                    },
                    "shrinkableContainer": {},
                    "minHeight": {},
                    "collapsed": {},
                    "containerHeightMargin": {}
                },
                "editorData": {
                    "testScreens": {
                        "initial": {
                            "deviceName": "LAPTOP",
                            "screenDimensions": {
                                "width": 1280,
                                "height": 800
                            }
                        },
                        "rendered": {
                            "deviceName": "LAPTOP",
                            "screenDimensions": {
                                "width": 1280,
                                "height": 800
                            }
                        }
                    },
                    "renderedStructure": {
                        "id": "page",
                        "layout": {
                            "x": 0,
                            "y": 0,
                            "width": 1265,
                            "height": 500
                        },
                        "children": [
                            {
                                "id": "comp-879d",
                                "layout": {
                                    "x": 100,
                                    "y": 100,
                                    "width": 100,
                                    "height": 90,
                                    "rotationInDegrees": 0
                                }
                            },
                            {
                                "id": "comp-2f45",
                                "layout": {
                                    "x": 100,
                                    "y": 170,
                                    "width": 100,
                                    "height": 60,
                                    "rotationInDegrees": 0
                                }
                            }
                        ]
                    },
                    "measuredRenderedScreenDimensions": {
                        "width": 1265,
                        "height": 800
                    },
                    "expectedStructure": {
                        "id": "page",
                        "layout": {
                            "x": 0,
                            "y": 0,
                            "width": 1265,
                            "height": 500,
                            "rotationInDegrees": 0
                        },
                        "children": [
                            {
                                "id": "comp-879d",
                                "layout": {
                                    "x": 100,
                                    "y": 100,
                                    "width": 100,
                                    "height": 90,
                                    "rotationInDegrees": 0
                                }
                            },
                            {
                                "id": "comp-2f45",
                                "layout": {
                                    "x": 100,
                                    "y": 200,
                                    "width": 100,
                                    "height": 60,
                                    "rotationInDegrees": 0
                                }
                            }
                        ]
                    }
                }
            },
            "runInBuild": true
        },
        "test_fd0c": {
            "id": "test_fd0c",
            "name": "Should not change top, if not locked anchor and gap is more then anchor DEFAULT_MARGIN",
            "testData": {
                "structure": {
                    "id": "page",
                    "layout": {
                        "x": 0,
                        "y": 0,
                        "width": 1265,
                        "height": 500
                    },
                    "children": [
                        {
                            "id": "comp-a740",
                            "layout": {
                                "x": 100,
                                "y": 100,
                                "width": 100,
                                "height": 60,
                                "rotationInDegrees": 0
                            }
                        },
                        {
                            "id": "comp-1ff8",
                            "layout": {
                                "x": 100,
                                "y": 300,
                                "width": 100,
                                "height": 60,
                                "rotationInDegrees": 0
                            }
                        }
                    ]
                },
                "measureMap": {
                    "width": {
                        "screen": 1265,
                        "page": 1265,
                        "comp-a740": 100,
                        "comp-1ff8": 100
                    },
                    "left": {
                        "page": 0,
                        "comp-a740": 100,
                        "comp-1ff8": 100
                    },
                    "height": {
                        "screen": 800,
                        "page": 500,
                        "comp-a740": 90,
                        "comp-1ff8": 60
                    },
                    "innerWidth": {
                        "screen": 1265,
                        "page": 1265,
                        "comp-a740": 100,
                        "comp-1ff8": 100
                    },
                    "clientHeight": 800,
                    "fixed": {
                        "page": false,
                        "comp-a740": false,
                        "comp-1ff8": false
                    },
                    "top": {
                        "page": 0,
                        "comp-a740": 100,
                        "comp-1ff8": 300
                    },
                    "clientWidth": 1265,
                    "innerHeight": {
                        "screen": 800,
                        "page": 500,
                        "comp-a740": 90,
                        "comp-1ff8": 60
                    },
                    "absoluteTop": {
                        "page": 0,
                        "comp-a740": 100,
                        "comp-1ff8": 300
                    },
                    "absoluteLeft": {
                        "page": 0,
                        "comp-a740": 100,
                        "comp-1ff8": 100
                    },
                    "shrinkableContainer": {},
                    "minHeight": {},
                    "collapsed": {},
                    "containerHeightMargin": {}
                },
                "expectedMeasureMap": {
                    "width": {
                        "screen": 1265,
                        "page": 1265,
                        "comp-a740": 100,
                        "comp-1ff8": 100
                    },
                    "left": {
                        "page": 0,
                        "comp-a740": 100,
                        "comp-1ff8": 100
                    },
                    "height": {
                        "screen": 800,
                        "page": 500,
                        "comp-a740": 90,
                        "comp-1ff8": 60
                    },
                    "innerWidth": {
                        "screen": 1265,
                        "page": 1265,
                        "comp-a740": 100,
                        "comp-1ff8": 100
                    },
                    "clientHeight": 800,
                    "fixed": {
                        "page": false,
                        "comp-a740": false,
                        "comp-1ff8": false
                    },
                    "top": {
                        "page": 0,
                        "comp-a740": 100,
                        "comp-1ff8": 300
                    },
                    "clientWidth": 1265,
                    "innerHeight": {
                        "screen": 800,
                        "page": 500,
                        "comp-a740": 90,
                        "comp-1ff8": 60
                    },
                    "absoluteTop": {
                        "page": 0,
                        "comp-a740": 100,
                        "comp-1ff8": 300
                    },
                    "absoluteLeft": {
                        "page": 0,
                        "comp-a740": 100,
                        "comp-1ff8": 100
                    },
                    "shrinkableContainer": {},
                    "minHeight": {},
                    "collapsed": {},
                    "containerHeightMargin": {}
                },
                "editorData": {
                    "testScreens": {
                        "initial": {
                            "deviceName": "LAPTOP",
                            "screenDimensions": {
                                "width": 1280,
                                "height": 800
                            }
                        },
                        "rendered": {
                            "deviceName": "LAPTOP",
                            "screenDimensions": {
                                "width": 1280,
                                "height": 800
                            }
                        }
                    },
                    "renderedStructure": {
                        "id": "page",
                        "layout": {
                            "x": 0,
                            "y": 0,
                            "width": 1265,
                            "height": 500
                        },
                        "children": [
                            {
                                "id": "comp-a740",
                                "layout": {
                                    "x": 100,
                                    "y": 100,
                                    "width": 100,
                                    "height": 90,
                                    "rotationInDegrees": 0
                                }
                            },
                            {
                                "id": "comp-1ff8",
                                "layout": {
                                    "x": 100,
                                    "y": 300,
                                    "width": 100,
                                    "height": 60,
                                    "rotationInDegrees": 0
                                }
                            }
                        ]
                    },
                    "measuredRenderedScreenDimensions": {
                        "width": 1265,
                        "height": 800
                    },
                    "expectedStructure": {
                        "id": "page",
                        "layout": {
                            "x": 0,
                            "y": 0,
                            "width": 1265,
                            "height": 500,
                            "rotationInDegrees": 0
                        },
                        "children": [
                            {
                                "id": "comp-a740",
                                "layout": {
                                    "x": 100,
                                    "y": 100,
                                    "width": 100,
                                    "height": 90,
                                    "rotationInDegrees": 0
                                }
                            },
                            {
                                "id": "comp-1ff8",
                                "layout": {
                                    "x": 100,
                                    "y": 300,
                                    "width": 100,
                                    "height": 60,
                                    "rotationInDegrees": 0
                                }
                            }
                        ]
                    }
                }
            },
            "runInBuild": true
        },
        "test_fd0d": {
            "id": "test_fd0d",
            "name": "Should change top, if not locked anchor and gap is less then anchor DEFAULT_MARGIN",
            "testData": {
                "structure": {
                    "id": "page",
                    "layout": {
                        "x": 0,
                        "y": 0,
                        "width": 1265,
                        "height": 500
                    },
                    "children": [
                        {
                            "id": "comp-a740",
                            "layout": {
                                "x": 100,
                                "y": 100,
                                "width": 100,
                                "height": 60,
                                "rotationInDegrees": 0
                            }
                        },
                        {
                            "id": "comp-1ff8",
                            "layout": {
                                "x": 100,
                                "y": 300,
                                "width": 100,
                                "height": 60,
                                "rotationInDegrees": 0
                            }
                        }
                    ]
                },
                "measureMap": {
                    "width": {
                        "screen": 1265,
                        "page": 1265,
                        "comp-a740": 100,
                        "comp-1ff8": 100
                    },
                    "left": {
                        "page": 0,
                        "comp-a740": 100,
                        "comp-1ff8": 100
                    },
                    "height": {
                        "screen": 800,
                        "page": 500,
                        "comp-a740": 200,
                        "comp-1ff8": 60
                    },
                    "innerWidth": {
                        "screen": 1265,
                        "page": 1265,
                        "comp-a740": 100,
                        "comp-1ff8": 100
                    },
                    "clientHeight": 800,
                    "fixed": {
                        "page": false,
                        "comp-a740": false,
                        "comp-1ff8": false
                    },
                    "top": {
                        "page": 0,
                        "comp-a740": 100,
                        "comp-1ff8": 300
                    },
                    "clientWidth": 1265,
                    "innerHeight": {
                        "screen": 800,
                        "page": 500,
                        "comp-a740": 200,
                        "comp-1ff8": 60
                    },
                    "absoluteTop": {
                        "page": 0,
                        "comp-a740": 100,
                        "comp-1ff8": 300
                    },
                    "absoluteLeft": {
                        "page": 0,
                        "comp-a740": 100,
                        "comp-1ff8": 100
                    },
                    "shrinkableContainer": {},
                    "minHeight": {},
                    "collapsed": {},
                    "containerHeightMargin": {}
                },
                "expectedMeasureMap": {
                    "width": {
                        "screen": 1265,
                        "page": 1265,
                        "comp-a740": 100,
                        "comp-1ff8": 100
                    },
                    "left": {
                        "page": 0,
                        "comp-a740": 100,
                        "comp-1ff8": 100
                    },
                    "height": {
                        "screen": 800,
                        "page": 500,
                        "comp-a740": 200,
                        "comp-1ff8": 60
                    },
                    "innerWidth": {
                        "screen": 1265,
                        "page": 1265,
                        "comp-a740": 100,
                        "comp-1ff8": 100
                    },
                    "clientHeight": 800,
                    "fixed": {
                        "page": false,
                        "comp-a740": false,
                        "comp-1ff8": false
                    },
                    "top": {
                        "page": 0,
                        "comp-a740": 100,
                        "comp-1ff8": 310
                    },
                    "clientWidth": 1265,
                    "innerHeight": {
                        "screen": 800,
                        "page": 500,
                        "comp-a740": 200,
                        "comp-1ff8": 60
                    },
                    "absoluteTop": {
                        "page": 0,
                        "comp-a740": 100,
                        "comp-1ff8": 300
                    },
                    "absoluteLeft": {
                        "page": 0,
                        "comp-a740": 100,
                        "comp-1ff8": 100
                    },
                    "shrinkableContainer": {},
                    "minHeight": {},
                    "collapsed": {},
                    "containerHeightMargin": {}
                },
                "editorData": {
                    "testScreens": {
                        "initial": {
                            "deviceName": "LAPTOP",
                            "screenDimensions": {
                                "width": 1280,
                                "height": 800
                            }
                        },
                        "rendered": {
                            "deviceName": "LAPTOP",
                            "screenDimensions": {
                                "width": 1280,
                                "height": 800
                            }
                        }
                    },
                    "renderedStructure": {
                        "id": "page",
                        "layout": {
                            "x": 0,
                            "y": 0,
                            "width": 1265,
                            "height": 500
                        },
                        "children": [
                            {
                                "id": "comp-a740",
                                "layout": {
                                    "x": 100,
                                    "y": 100,
                                    "width": 100,
                                    "height": 200,
                                    "rotationInDegrees": 0
                                }
                            },
                            {
                                "id": "comp-1ff8",
                                "layout": {
                                    "x": 100,
                                    "y": 300,
                                    "width": 100,
                                    "height": 60,
                                    "rotationInDegrees": 0
                                }
                            }
                        ]
                    },
                    "measuredRenderedScreenDimensions": {
                        "width": 1265,
                        "height": 800
                    },
                    "expectedStructure": {
                        "id": "page",
                        "layout": {
                            "x": 0,
                            "y": 0,
                            "width": 1265,
                            "height": 500,
                            "rotationInDegrees": 0
                        },
                        "children": [
                            {
                                "id": "comp-a740",
                                "layout": {
                                    "x": 100,
                                    "y": 100,
                                    "width": 100,
                                    "height": 200,
                                    "rotationInDegrees": 0
                                }
                            },
                            {
                                "id": "comp-1ff8",
                                "layout": {
                                    "x": 100,
                                    "y": 310,
                                    "width": 100,
                                    "height": 60,
                                    "rotationInDegrees": 0
                                }
                            }
                        ]
                    }
                }
            },
            "runInBuild": true
        },
        "test_08fe": {
            "id": "test_08fe",
            "name": "Should decrease top as needed if anchor locked",
            "testData": {
                "structure": {
                    "id": "page",
                    "layout": {
                        "x": 0,
                        "y": 0,
                        "width": 1265,
                        "height": 500
                    },
                    "children": [
                        {
                            "id": "comp-e2b3",
                            "layout": {
                                "x": 100,
                                "y": 100,
                                "width": 100,
                                "height": 60,
                                "rotationInDegrees": 0
                            }
                        },
                        {
                            "id": "comp-257b",
                            "layout": {
                                "x": 100,
                                "y": 170,
                                "width": 100,
                                "height": 60,
                                "rotationInDegrees": 0
                            }
                        }
                    ]
                },
                "measureMap": {
                    "width": {
                        "screen": 1265,
                        "page": 1265,
                        "comp-e2b3": 100,
                        "comp-257b": 100
                    },
                    "left": {
                        "page": 0,
                        "comp-e2b3": 100,
                        "comp-257b": 100
                    },
                    "height": {
                        "screen": 800,
                        "page": 500,
                        "comp-e2b3": 50,
                        "comp-257b": 60
                    },
                    "innerWidth": {
                        "screen": 1265,
                        "page": 1265,
                        "comp-e2b3": 100,
                        "comp-257b": 100
                    },
                    "clientHeight": 800,
                    "fixed": {
                        "page": false,
                        "comp-e2b3": false,
                        "comp-257b": false
                    },
                    "top": {
                        "page": 0,
                        "comp-e2b3": 100,
                        "comp-257b": 170
                    },
                    "clientWidth": 1265,
                    "innerHeight": {
                        "screen": 800,
                        "page": 500,
                        "comp-e2b3": 50,
                        "comp-257b": 60
                    },
                    "absoluteTop": {
                        "page": 0,
                        "comp-e2b3": 100,
                        "comp-257b": 170
                    },
                    "absoluteLeft": {
                        "page": 0,
                        "comp-e2b3": 100,
                        "comp-257b": 100
                    },
                    "shrinkableContainer": {},
                    "minHeight": {},
                    "collapsed": {},
                    "containerHeightMargin": {}
                },
                "expectedMeasureMap": {
                    "width": {
                        "screen": 1265,
                        "page": 1265,
                        "comp-e2b3": 100,
                        "comp-257b": 100
                    },
                    "left": {
                        "page": 0,
                        "comp-e2b3": 100,
                        "comp-257b": 100
                    },
                    "height": {
                        "screen": 800,
                        "page": 500,
                        "comp-e2b3": 50,
                        "comp-257b": 60
                    },
                    "innerWidth": {
                        "screen": 1265,
                        "page": 1265,
                        "comp-e2b3": 100,
                        "comp-257b": 100
                    },
                    "clientHeight": 800,
                    "fixed": {
                        "page": false,
                        "comp-e2b3": false,
                        "comp-257b": false
                    },
                    "top": {
                        "page": 0,
                        "comp-e2b3": 100,
                        "comp-257b": 160
                    },
                    "clientWidth": 1265,
                    "innerHeight": {
                        "screen": 800,
                        "page": 500,
                        "comp-e2b3": 50,
                        "comp-257b": 60
                    },
                    "absoluteTop": {
                        "page": 0,
                        "comp-e2b3": 100,
                        "comp-257b": 170
                    },
                    "absoluteLeft": {
                        "page": 0,
                        "comp-e2b3": 100,
                        "comp-257b": 100
                    },
                    "shrinkableContainer": {},
                    "minHeight": {},
                    "collapsed": {},
                    "containerHeightMargin": {}
                },
                "editorData": {
                    "testScreens": {
                        "initial": {
                            "deviceName": "LAPTOP",
                            "screenDimensions": {
                                "width": 1280,
                                "height": 800
                            }
                        },
                        "rendered": {
                            "deviceName": "LAPTOP",
                            "screenDimensions": {
                                "width": 1280,
                                "height": 800
                            }
                        }
                    },
                    "renderedStructure": {
                        "id": "page",
                        "layout": {
                            "x": 0,
                            "y": 0,
                            "width": 1265,
                            "height": 500
                        },
                        "children": [
                            {
                                "id": "comp-e2b3",
                                "layout": {
                                    "x": 100,
                                    "y": 100,
                                    "width": 100,
                                    "height": 50,
                                    "rotationInDegrees": 0
                                }
                            },
                            {
                                "id": "comp-257b",
                                "layout": {
                                    "x": 100,
                                    "y": 170,
                                    "width": 100,
                                    "height": 60,
                                    "rotationInDegrees": 0
                                }
                            }
                        ]
                    },
                    "measuredRenderedScreenDimensions": {
                        "width": 1265,
                        "height": 800
                    },
                    "expectedStructure": {
                        "id": "page",
                        "layout": {
                            "x": 0,
                            "y": 0,
                            "width": 1265,
                            "height": 500,
                            "rotationInDegrees": 0
                        },
                        "children": [
                            {
                                "id": "comp-e2b3",
                                "layout": {
                                    "x": 100,
                                    "y": 100,
                                    "width": 100,
                                    "height": 50,
                                    "rotationInDegrees": 0
                                }
                            },
                            {
                                "id": "comp-257b",
                                "layout": {
                                    "x": 100,
                                    "y": 160,
                                    "width": 100,
                                    "height": 60,
                                    "rotationInDegrees": 0
                                }
                            }
                        ]
                    }
                }
            },
            "runInBuild": true
        },
        "test_08ff": {
            "id": "test_08ff",
            "name": "Should not decrease top if anchor not locked",
            "testData": {
                "structure": {
                    "id": "page",
                    "layout": {
                        "x": 0,
                        "y": 0,
                        "width": 1265,
                        "height": 500
                    },
                    "children": [
                        {
                            "id": "comp-e2b3",
                            "layout": {
                                "x": 100,
                                "y": 100,
                                "width": 100,
                                "height": 60,
                                "rotationInDegrees": 0
                            }
                        },
                        {
                            "id": "comp-257b",
                            "layout": {
                                "x": 100,
                                "y": 270,
                                "width": 100,
                                "height": 60,
                                "rotationInDegrees": 0
                            }
                        }
                    ]
                },
                "measureMap": {
                    "width": {
                        "screen": 1265,
                        "page": 1265,
                        "comp-e2b3": 100,
                        "comp-257b": 100
                    },
                    "left": {
                        "page": 0,
                        "comp-e2b3": 100,
                        "comp-257b": 100
                    },
                    "height": {
                        "screen": 800,
                        "page": 500,
                        "comp-e2b3": 40,
                        "comp-257b": 60
                    },
                    "innerWidth": {
                        "screen": 1265,
                        "page": 1265,
                        "comp-e2b3": 100,
                        "comp-257b": 100
                    },
                    "clientHeight": 800,
                    "fixed": {
                        "page": false,
                        "comp-e2b3": false,
                        "comp-257b": false
                    },
                    "top": {
                        "page": 0,
                        "comp-e2b3": 100,
                        "comp-257b": 270
                    },
                    "clientWidth": 1265,
                    "innerHeight": {
                        "screen": 800,
                        "page": 500,
                        "comp-e2b3": 40,
                        "comp-257b": 60
                    },
                    "absoluteTop": {
                        "page": 0,
                        "comp-e2b3": 100,
                        "comp-257b": 270
                    },
                    "absoluteLeft": {
                        "page": 0,
                        "comp-e2b3": 100,
                        "comp-257b": 100
                    },
                    "shrinkableContainer": {},
                    "minHeight": {},
                    "collapsed": {},
                    "containerHeightMargin": {}
                },
                "expectedMeasureMap": {
                    "width": {
                        "screen": 1265,
                        "page": 1265,
                        "comp-e2b3": 100,
                        "comp-257b": 100
                    },
                    "left": {
                        "page": 0,
                        "comp-e2b3": 100,
                        "comp-257b": 100
                    },
                    "height": {
                        "screen": 800,
                        "page": 500,
                        "comp-e2b3": 40,
                        "comp-257b": 60
                    },
                    "innerWidth": {
                        "screen": 1265,
                        "page": 1265,
                        "comp-e2b3": 100,
                        "comp-257b": 100
                    },
                    "clientHeight": 800,
                    "fixed": {
                        "page": false,
                        "comp-e2b3": false,
                        "comp-257b": false
                    },
                    "top": {
                        "page": 0,
                        "comp-e2b3": 100,
                        "comp-257b": 270
                    },
                    "clientWidth": 1265,
                    "innerHeight": {
                        "screen": 800,
                        "page": 500,
                        "comp-e2b3": 40,
                        "comp-257b": 60
                    },
                    "absoluteTop": {
                        "page": 0,
                        "comp-e2b3": 100,
                        "comp-257b": 270
                    },
                    "absoluteLeft": {
                        "page": 0,
                        "comp-e2b3": 100,
                        "comp-257b": 100
                    },
                    "shrinkableContainer": {},
                    "minHeight": {},
                    "collapsed": {},
                    "containerHeightMargin": {}
                },
                "editorData": {
                    "testScreens": {
                        "initial": {
                            "deviceName": "LAPTOP",
                            "screenDimensions": {
                                "width": 1280,
                                "height": 800
                            }
                        },
                        "rendered": {
                            "deviceName": "LAPTOP",
                            "screenDimensions": {
                                "width": 1280,
                                "height": 800
                            }
                        }
                    },
                    "renderedStructure": {
                        "id": "page",
                        "layout": {
                            "x": 0,
                            "y": 0,
                            "width": 1265,
                            "height": 500
                        },
                        "children": [
                            {
                                "id": "comp-e2b3",
                                "layout": {
                                    "x": 100,
                                    "y": 100,
                                    "width": 100,
                                    "height": 40,
                                    "rotationInDegrees": 0
                                }
                            },
                            {
                                "id": "comp-257b",
                                "layout": {
                                    "x": 100,
                                    "y": 270,
                                    "width": 100,
                                    "height": 60,
                                    "rotationInDegrees": 0
                                }
                            }
                        ]
                    },
                    "measuredRenderedScreenDimensions": {
                        "width": 1265,
                        "height": 800
                    },
                    "expectedStructure": {
                        "id": "page",
                        "layout": {
                            "x": 0,
                            "y": 0,
                            "width": 1265,
                            "height": 500,
                            "rotationInDegrees": 0
                        },
                        "children": [
                            {
                                "id": "comp-e2b3",
                                "layout": {
                                    "x": 100,
                                    "y": 100,
                                    "width": 100,
                                    "height": 40,
                                    "rotationInDegrees": 0
                                }
                            },
                            {
                                "id": "comp-257b",
                                "layout": {
                                    "x": 100,
                                    "y": 270,
                                    "width": 100,
                                    "height": 60,
                                    "rotationInDegrees": 0
                                }
                            }
                        ]
                    }
                }
            },
            "runInBuild": true
        },
        "test_f750": {
            "id": "test_f750",
            "name": "[Todo] - Should not decrease top to less the original value",
            "testData": {},
            "runInBuild": true
        },
        "test_3f80": {
            "id": "test_3f80",
            "name": "[Todo] - Should push component only in integer number for not locke anchor",
            "testData": {},
            "runInBuild": true
        },
        "test_3f81": {
            "id": "test_3f81",
            "name": "[Todo] - Should push component only in integer number for locked anchor",
            "testData": {},
            "runInBuild": true
        }
    },
    "experiments": {
        "layout_verbs_with_anchors": 1
    }
}